manim_kodisc/__init__.py
manim_kodisc/card.py
manim_kodisc/force_diagram.py
manim_kodisc/geometry/__init__.py
manim_kodisc/geometry/polygon.py
manim_kodisc/geometry/regular_polygon.py
manim_kodisc/particle_simulation.py
manim_kodisc/pi_chart.py
manim_kodisc/rotating_function.py
manim_kodisc/slope_field.py
manim_kodisc/web_image.py
manim_kodisc/web_svg.py
manim_kodisc-1.1.5.dist-info/entry_points.txt
manim_kodisc-1.1.5.dist-info/METADATA
manim_kodisc-1.1.5.dist-info/WHEEL
manim_kodisc-1.1.5.dist-info/RECORD
