Metadata-Version: 2.3
Name: manim-kodisc
Version: 1.1.5
Summary: Manim plugin for Kodisc
Author: LandonHarter
Author-email: landonharter@outlook.com
Requires-Python: >=3.11
Classifier: Programming Language :: Python :: 3
Classifier: Programming Language :: Python :: 3.11
Classifier: Programming Language :: Python :: 3.12
Classifier: Programming Language :: Python :: 3.13
Requires-Dist: pillow (>=9.0.0,<10.0.0)
